{
    "tournament": {
        "name": "Premier League 23/24",
        "slug": "premier-league-23/24",
        "category": {
            "name": "England",
            "slug": "england",
            "sport": {
                "name": "Football",
                "slug": "football",
                "_id": {
                    "$oid": "64fa9de872175c9663ba1f3a"
                }
            },
            "_id": {
                "$oid": "64fa9e3972175c9663ba1f3c"
            }
        },
        "uniqueTournament": {
            "name": "Premier League",
            "slug": "premier-league",
            "category": {
                "name": "England",
                "slug": "england",
                "sport": {
                    "name": "Football",
                    "slug": "football",
                    "_id": {
                        "$oid": "64fa9de872175c9663ba1f3a"
                    }
                },
                "_id": {
                    "$oid": "64fa9e3972175c9663ba1f3c"
                }
            },
            "userCount": 1293862,
            "image": "",
            "_id": {
                "$oid": "64fe7c4e4083769fbfe885f7"
            }
        },
        "image": "",
        "_id": {
            "$oid": "64fad93972175c9663ba1f7e"
        }
    },
    "status": {
        "code": 0,
        "description": "Not started",
        "type": "notstarted"
    },
    "homeTeam": {
        "name": "Aston Villa",
        "slug": "aston-villa",
        "shortName": "Aston Villa",
        "sport": {
            "name": "Football",
            "slug": "football",
            "_id": {
                "$oid": "64fa9de872175c9663ba1f3a"
            }
        },
        "userCount": 185507,
        "nameCode": "AVL",
        "country": {
            "_id": {
                "$oid": "64faa02272175c9663ba1f48"
            },
            "name": "England",
            "slug": "england",
            "alpha2": "EN"
        },
        "image": "",
        "_id": {
            "$oid": "64face3c72175c9663ba1f66"
        }
    },
    "awayTeam": {
        "name": "Brighton & Hove Albion",
        "slug": "brighton-and-hove-albion",
        "shortName": "Brighton",
        "sport": {
            "name": "Football",
            "slug": "football",
            "_id": {
                "$oid": "64fa9de872175c9663ba1f3a"
            }
        },
        "userCount": 188358,
        "nameCode": "BHA",
        "country": {
            "_id": {
                "$oid": "64faa02272175c9663ba1f48"
            },
            "name": "England",
            "slug": "england",
            "alpha2": "EN"
        },
        "image": "",
        "_id": {
            "$oid": "64face2c72175c9663ba1f62"
        }
    },
    "homeScore": {},
    "awayScore": {},
    "time": {},
    "startTimestamp": 1696073400,
    "slug": "aston-villa-brighton-and-hove-albion",
    "round": 7
}